pyawsopstoolkit/__init__.py
pyawsopstoolkit/__validations__.py
pyawsopstoolkit/account.py
pyawsopstoolkit/credentials.py
pyawsopstoolkit/exceptions.py
pyawsopstoolkit/session.py
pyawsopstoolkit-0.1.19.dist-info/LICENSE
pyawsopstoolkit-0.1.19.dist-info/METADATA
pyawsopstoolkit-0.1.19.dist-info/WHEEL
pyawsopstoolkit-0.1.19.dist-info/top_level.txt
pyawsopstoolkit-0.1.19.dist-info/RECORD
