Metadata-Version: 2.1
Name: pyawsopstoolkit
Version: 0.1.19
Summary: This extensive package, AWS Ops Toolkit, offers a wide range of features and enhancements designed to streamline and
Home-page: https://github.com/coldsofttech/pyawsopstoolkit.git
Author: coldsofttech
License: MIT
Keywords: aws,toolkit,operations,tools,development,python,session-management,utilities,enhancements,integration,amazon-web-services
Classifier: Development Status :: 4 - Beta
Classifier: Intended Audience :: Developers
Classifier: Topic :: Software Development :: Libraries
Classifier: Topic :: Software Development :: Libraries :: Python Modules
Classifier: License :: OSI Approved :: MIT License
Classifier: Programming Language :: Python :: 3.10
Classifier: Programming Language :: Python :: 3.11
Classifier: Programming Language :: Python :: 3.12
License-File: LICENSE
Requires-Dist: pyawsopstoolkit-validators==0.1.0
Requires-Dist: boto3==1.34.158
Requires-Dist: botocore==1.34.158
